tet/deform/__init__.py
tet.deform-0.1.dist-info/DESCRIPTION.rst
tet.deform-0.1.dist-info/METADATA
tet.deform-0.1.dist-info/RECORD
tet.deform-0.1.dist-info/WHEEL
tet.deform-0.1.dist-info/metadata.json
tet.deform-0.1.dist-info/top_level.txt
